LICENSE
MANIFEST.in
README.rst
setup.py
django_average/__init__.py
django_average/admin.py
django_average/apps.py
django_average/models.py
django_average/tests.py
django_average/views.py
django_average.egg-info/PKG-INFO
django_average.egg-info/SOURCES.txt
django_average.egg-info/dependency_links.txt
django_average.egg-info/top_level.txt
django_average/data_statistic/__init__.py
django_average/data_statistic/admin.py
django_average/data_statistic/apps.py
django_average/data_statistic/models.py
django_average/data_statistic/tests.py
django_average/data_statistic/views.py
django_average/observer/__init__.py
django_average/observer/admin.py
django_average/observer/apps.py
django_average/observer/models.py
django_average/observer/tests.py
django_average/observer/views.py
django_average/statistic_time/__init__.py
django_average/statistic_time/admin.py
django_average/statistic_time/apps.py
django_average/statistic_time/models.py
django_average/statistic_time/tests.py
django_average/statistic_time/views.py